kthutils/Makefile
kthutils/__init__.py
kthutils/cli.nw
kthutils/cli.py
kthutils/credentials.py
kthutils/forms.nw
kthutils/forms.py
kthutils/iprange.nw
kthutils/iprange.py
kthutils/iprange.sh
kthutils/participants.nw
kthutils/participants.py
kthutils/restlabb.sh
kthutils/restlabbsetup.sh
kthutils/ug.nw
kthutils/ug.py
kthutils-1.31.dist-info/METADATA
kthutils-1.31.dist-info/WHEEL
kthutils-1.31.dist-info/entry_points.txt
kthutils-1.31.dist-info/licenses/LICENSE
kthutils-1.31.dist-info/RECORD
