Metadata-Version: 2.4
Name: kthutils
Version: 1.31
Summary: Various tools for automation at KTH
License-Expression: MIT
License-File: LICENSE
Author: Daniel Bosk
Author-email: dbosk@kth.se
Requires-Python: >=3.8,<4.0
Classifier: Programming Language :: Python :: 3
Classifier: Programming Language :: Python :: 3.8
Classifier: Programming Language :: Python :: 3.9
Classifier: Programming Language :: Python :: 3.10
Classifier: Programming Language :: Python :: 3.11
Classifier: Programming Language :: Python :: 3.12
Classifier: Programming Language :: Python :: 3.13
Classifier: Programming Language :: Python :: 3.14
Requires-Dist: cachetools (>=5.2.0,<6.0)
Requires-Dist: ladok3 (>=5.5,<6.0)
Requires-Dist: openpyxl (>=3.1.2,<4.0)
Requires-Dist: rich (>=13.3.2,<14.0)
Requires-Dist: typer (>=0.9.0,<1.0)
Requires-Dist: typerconf (>=2.10,<3.0)
Requires-Dist: typing-extensions (>=4.9.0,<5.0) ; python_version < "3.9"
Requires-Dist: weblogin (>=1.13,<2.0)
Project-URL: Bug Tracker, https://github.com/dbosk/kthutils/issues
Project-URL: Documentation, https://github.com/dbosk/kthutils/releases
Project-URL: Repository, https://github.com/dbosk/kthutils
